sipyconfig/__init__.py
sipyconfig/card.py
sipyconfig/comms.py
sipyconfig/crc.py
sipyconfig/enums.py
sipyconfig/py.typed
sipyconfig/station.py
sipyconfig/utils.py
sipyconfig-1.2.3.dist-info/licenses/LICENSE
sipyconfig-1.2.3.dist-info/METADATA
sipyconfig-1.2.3.dist-info/WHEEL
sipyconfig-1.2.3.dist-info/top_level.txt
sipyconfig-1.2.3.dist-info/RECORD
