Metadata-Version: 2.4
Name: sipyconfig
Version: 1.2.3
Summary: Python replacement for the functionality of SportIdent Config+
Author-email: Teichi <tobias@teichmann.top>
License: GPL-3.0-only
Project-URL: Homepage, https://gitlab.com/Teigi/sipyconfig
Classifier: Programming Language :: Python :: 3
Classifier: License :: OSI Approved :: GNU General Public License v3 (GPLv3)
Classifier: Operating System :: Unix
Classifier: Typing :: Typed
Classifier: Topic :: Utilities
Classifier: Development Status :: 4 - Beta
Requires-Python: >=3.10
License-File: LICENSE
Requires-Dist: pyserial
Dynamic: license-file
